main_threaded.py
pdfmirror-0.1.0.dist-info/METADATA
pdfmirror-0.1.0.dist-info/WHEEL
pdfmirror-0.1.0.dist-info/entry_points.txt
pdfmirror-0.1.0.dist-info/top_level.txt
pdfmirror-0.1.0.dist-info/RECORD
