Metadata-Version: 2.1
Name: pdfmirror
Version: 0.1.0
Summary: A CLI tool to mirror a pdf
Home-page: https://github.com/hkievet/pdfmirror
Author: Hunter Kievet
Classifier: Programming Language :: Python :: 3
Classifier: License :: OSI Approved :: MIT License
Classifier: Operating System :: OS Independent
Requires-Python: >=3.6
